RTS_Remotetummelsystem/__init__.py
RTS_Remotetummelsystem/client.py
RTS_Remotetummelsystem/server.py
RTS_Remotetummelsystem/snowflake.py
RTS_Tunnel-0.4.dist-info/LICENCE
RTS_Tunnel-0.4.dist-info/METADATA
RTS_Tunnel-0.4.dist-info/WHEEL
RTS_Tunnel-0.4.dist-info/top_level.txt
RTS_Tunnel-0.4.dist-info/RECORD
