Metadata-Version: 2.1
Name: RTS-Tunnel
Version: 0.4
Summary: Work in progress, a tunneling system for RTS_DataBase.
Home-page: https://github.com/RandomTimeLP/RTS_DataBase/
Author: RandomTimeTV
Author-email: dergepanzerte1@gmail.com
License: MIT with required credit to the author.
Keywords: database
Platform: UNKNOWN
Classifier: Development Status :: 3 - Alpha
Classifier: License :: OSI Approved :: MIT License
Classifier: Programming Language :: Python :: 3.6
Classifier: Programming Language :: Python :: 3.7
Classifier: Programming Language :: Python :: 3.8
Classifier: Programming Language :: Python :: 3.9
License-File: LICENCE
Requires-Dist: scapy
Requires-Dist: extrautilities
Requires-Dist: prompt-toolkit
